Metadata-Version: 2.1
Name: newone
Version: 0.4
Summary: Gaussian distributions
Home-page: UNKNOWN
Author: abc
Author-email: anceeff@gmail.com
License: UNKNOWN
Platform: UNKNOWN
